trevorproxy/__init__.py
trevorproxy/cli.py
trevorproxy/lib/cyclic.py
trevorproxy/lib/errors.py
trevorproxy/lib/logger.py
trevorproxy/lib/requests_wrapper.py
trevorproxy/lib/socks.py
trevorproxy/lib/ssh.py
trevorproxy/lib/subnet.py
trevorproxy/lib/util.py
trevorproxy-1.0.9.dist-info/LICENSE
trevorproxy-1.0.9.dist-info/METADATA
trevorproxy-1.0.9.dist-info/WHEEL
trevorproxy-1.0.9.dist-info/entry_points.txt
trevorproxy-1.0.9.dist-info/RECORD
